src/__init__.py
src/engrproblems.py
engrproblems-2.1.dist-info/LICENSE
engrproblems-2.1.dist-info/METADATA
engrproblems-2.1.dist-info/WHEEL
engrproblems-2.1.dist-info/top_level.txt
engrproblems-2.1.dist-info/RECORD
