Metadata-Version: 2.1
Name: engrproblems
Version: 2.1
Summary: ENGR 103 HW package, my first Programming package 
Home-page: UNKNOWN
Author: Ryan Hopkins
Author-email: hopkinsr@oregonstate.edu
License: UNKNOWN
Keywords: python,first package,Engr 103,OSU,ENGR 103 HW
Platform: UNKNOWN
Classifier: Development Status :: 3 - Alpha
Classifier: Intended Audience :: Education
Classifier: Programming Language :: Python :: 2
Classifier: Programming Language :: Python :: 3
Classifier: Operating System :: MacOS :: MacOS X
Classifier: Operating System :: Microsoft :: Windows
